taskify/__init__.py
taskify/main.py
taskify/storage.py
taskify/task_manager.py
heytaskify-1.0.7.dist-info/METADATA
heytaskify-1.0.7.dist-info/WHEEL
heytaskify-1.0.7.dist-info/entry_points.txt
heytaskify-1.0.7.dist-info/top_level.txt
heytaskify-1.0.7.dist-info/RECORD
